simplabel/__init__.py
simplabel/flow_to_directory.py
simplabel/simplabel.py
simplabel/utils.py
simplabel-0.1.5.dist-info/LICENSE
simplabel-0.1.5.dist-info/METADATA
simplabel-0.1.5.dist-info/WHEEL
simplabel-0.1.5.dist-info/entry_points.txt
simplabel-0.1.5.dist-info/top_level.txt
simplabel-0.1.5.dist-info/RECORD
