Metadata-Version: 2.1
Name: simplabel
Version: 0.1.5
Summary: Simple tool to manually label images in disctinct categories.
Home-page: https://github.com/hlgirard/Simplabel
Author: Henri-Louis Girard
Author-email: hl.girard@gmail.com
License: GPLv3
Platform: UNKNOWN
Requires-Dist: pillow (>=6.0.0)
